cantera_adaptive_testing/__init__.py
cantera_adaptive_testing/commandline.py
cantera_adaptive_testing/mechanism_base.py
cantera_adaptive_testing/mechanisms.py
cantera_adaptive_testing/plotter.py
cantera_adaptive_testing/utilities.py
cantera_adaptive_testing/mechanisms/3-methylheptane-c8h18-3-1378-8143.yaml
cantera_adaptive_testing/mechanisms/alkylaromatics-530.yaml
cantera_adaptive_testing/mechanisms/dme-propane-122.yaml
cantera_adaptive_testing/mechanisms/gas-def.yaml
cantera_adaptive_testing/mechanisms/gasoline-surrogate-1389.yaml
cantera_adaptive_testing/mechanisms/gri-mech-55.yaml
cantera_adaptive_testing/mechanisms/hydrogen-10.yaml
cantera_adaptive_testing/mechanisms/i-pentanol-511.yaml
cantera_adaptive_testing/mechanisms/ic8-874.yaml
cantera_adaptive_testing/mechanisms/jetA-detailed-NOx-203.yaml
cantera_adaptive_testing/mechanisms/md-nc7-3787.yaml
cantera_adaptive_testing/mechanisms/md5d-2649.yaml
cantera_adaptive_testing/mechanisms/md9d-3298.yaml
cantera_adaptive_testing/mechanisms/md9dnc7-3299.yaml
cantera_adaptive_testing/mechanisms/mmc5-7171-38324.yaml
cantera_adaptive_testing/mechanisms/mmc7-707-5505.yaml
cantera_adaptive_testing/mechanisms/n-dodecane-65.yaml
cantera_adaptive_testing/mechanisms/n-heptane-c7h16-654-4846.yaml
cantera_adaptive_testing/mechanisms/n-hexadecane-nc16-h34-2115-13339.yaml
cantera_adaptive_testing/mechanisms/plog-2.yaml
cantera_adaptive_testing/mechanisms/robertson.yaml
cantera_adaptive_testing-0.0.1.dist-info/LICENSE
cantera_adaptive_testing-0.0.1.dist-info/METADATA
cantera_adaptive_testing-0.0.1.dist-info/WHEEL
cantera_adaptive_testing-0.0.1.dist-info/entry_points.txt
cantera_adaptive_testing-0.0.1.dist-info/top_level.txt
cantera_adaptive_testing-0.0.1.dist-info/RECORD
