Metadata-Version: 2.1
Name: cantera-adaptive-testing
Version: 0.0.1
Summary: This package is used for testing preconditioner additions to Cantera and running studies on the additions.
Home-page: https://github.com/anthony-walker/cantera-adaptive-testing
Author: Anthony Walker
Author-email: walkanth@oregonstate.edu
License: MIT License
Platform: UNKNOWN
Classifier: Programming Language :: Python :: 3
Classifier: License :: OSI Approved :: BSD License
Classifier: Operating System :: OS Independent
Requires-Python: >=3.6
License-File: LICENSE
Requires-Dist: cantera
Requires-Dist: mpi4py
